{
  "project_info": {
    "project_number": "643249570230",
    "firebase_url": "https://doccare-app.firebaseio.com",
    "project_id": "doccare-app",
    "storage_bucket": "doccare-app.appspot.com"
  },
  "client": [
    {
      "client_info": {
        "mobilesdk_app_id": "1:643249570230:android:4dbca906fcf523ce",
        "android_client_info": {
          "package_name": "com.example.doccure"
        }
      },
      "oauth_client": [
        {
          "client_id": "643249570230-bspr7emup1rqkavtl655ip0nu4pvhs7p.apps.googleusercontent.com",
          "client_type": 1,
          "android_info": {
            "package_name": "com.example.doccure",
            "certificate_hash": "0cbef6beb256d709c51691f00892d813df03572e"
          }
        },
        {
          "client_id": "643249570230-gi2dvgppomgg9s5g6toctab5nouga8o2.apps.googleusercontent.com",
          "client_type": 3
        }
      ],
      "api_key": [
        {
          "current_key": "AIzaSyB68fYDImFxC3V19XJ_H7m1JxBPRjbIrxw"
        }
      ],
      "services": {
        "appinvite_service": {
          "other_platform_oauth_client": [
            {
              "client_id": "643249570230-gi2dvgppomgg9s5g6toctab5nouga8o2.apps.googleusercontent.com",
              "client_type": 3
            }
          ]
        }
      }
    }
  ],
  "configuration_version": "1"
}